rasterioxyz/__init__.py
rasterioxyz/_cli.py
rasterioxyz/_errors.py
rasterioxyz/_serve.py
rasterioxyz/tile.py
rasterioxyz-0.1.1.dist-info/licenses/LICENSE
rasterioxyz-0.1.1.dist-info/METADATA
rasterioxyz-0.1.1.dist-info/WHEEL
rasterioxyz-0.1.1.dist-info/entry_points.txt
rasterioxyz-0.1.1.dist-info/top_level.txt
rasterioxyz-0.1.1.dist-info/RECORD
