Metadata-Version: 2.4
Name: rasterioxyz
Version: 0.1.1
Summary: Package for tiling georeferenced Rasterio DatasetReader objects according to the XYZ tiles standard.
Project-URL: repository, https://github.com/duncanmartyn/rasterioxyz
Project-URL: issues, https://github.com/duncanmartyn/rasterioxyz/issues
Project-URL: changelog, https://github.com/duncanmartyn/rasterioxyz/blob/main/CHANGELOG.md
Requires-Python: >=3.13
License-File: LICENSE
Requires-Dist: rasterio>=1.4.3
Dynamic: license-file
